JujiZhenmingYuyouyiquTupo/README.md
JujiZhenmingYuyouyiquTupo/__init__.py
JujiZhenmingYuyouyiquTupo/__main__.py
JujiZhenmingYuyouyiquTupo/file.epub
JujiZhenmingYuyouyiquTupo/index.html
JujiZhenmingYuyouyiquTupo/css/__init__.py
JujiZhenmingYuyouyiquTupo/css/annotations.css
JujiZhenmingYuyouyiquTupo/css/main.css
JujiZhenmingYuyouyiquTupo/css/normalize.css
JujiZhenmingYuyouyiquTupo/css/popup.css
JujiZhenmingYuyouyiquTupo/font/__init__.py
JujiZhenmingYuyouyiquTupo/font/fontello.eot
JujiZhenmingYuyouyiquTupo/font/fontello.svg
JujiZhenmingYuyouyiquTupo/font/fontello.ttf
JujiZhenmingYuyouyiquTupo/font/fontello.woff
JujiZhenmingYuyouyiquTupo/img/__init__.py
JujiZhenmingYuyouyiquTupo/img/annotator-glyph-sprite.png
JujiZhenmingYuyouyiquTupo/img/annotator-icon-sprite.png
JujiZhenmingYuyouyiquTupo/img/apple-touch-icon.png
JujiZhenmingYuyouyiquTupo/img/cancelfullscreen.png
JujiZhenmingYuyouyiquTupo/img/close.png
JujiZhenmingYuyouyiquTupo/img/fullscreen.png
JujiZhenmingYuyouyiquTupo/img/loader.gif
JujiZhenmingYuyouyiquTupo/img/menu-icon.png
JujiZhenmingYuyouyiquTupo/img/save.png
JujiZhenmingYuyouyiquTupo/img/saved.png
JujiZhenmingYuyouyiquTupo/img/settings-s.png
JujiZhenmingYuyouyiquTupo/img/settings.png
JujiZhenmingYuyouyiquTupo/img/star.png
JujiZhenmingYuyouyiquTupo/js/__init__.py
JujiZhenmingYuyouyiquTupo/js/epub.js
JujiZhenmingYuyouyiquTupo/js/epub.min.js
JujiZhenmingYuyouyiquTupo/js/epub.min.map
JujiZhenmingYuyouyiquTupo/js/hooks.min.js
JujiZhenmingYuyouyiquTupo/js/hooks.min.map
JujiZhenmingYuyouyiquTupo/js/reader.js
JujiZhenmingYuyouyiquTupo/js/reader.js.map
JujiZhenmingYuyouyiquTupo/js/reader.min.js
JujiZhenmingYuyouyiquTupo/js/reader.min.map
JujiZhenmingYuyouyiquTupo/js/hooks/__init__.py
JujiZhenmingYuyouyiquTupo/js/hooks/extensions/__init__.py
JujiZhenmingYuyouyiquTupo/js/hooks/extensions/highlight.js
JujiZhenmingYuyouyiquTupo/js/libs/__init__.py
JujiZhenmingYuyouyiquTupo/js/libs/jquery.min.js
JujiZhenmingYuyouyiquTupo/js/libs/localforage.min.js
juji_zhenming_yuyouyiqu_tupo-2022.10.11.0.dist-info/METADATA
juji_zhenming_yuyouyiqu_tupo-2022.10.11.0.dist-info/WHEEL
juji_zhenming_yuyouyiqu_tupo-2022.10.11.0.dist-info/entry_points.txt
juji_zhenming_yuyouyiqu_tupo-2022.10.11.0.dist-info/top_level.txt
juji_zhenming_yuyouyiqu_tupo-2022.10.11.0.dist-info/RECORD
